torcheck/__init__.py
torcheck/output_spec.py
torcheck/param_spec.py
torcheck/registry.py
torcheck/utils/__init__.py
torcheck/utils/message_utils.py
torcheck-1.0.1.dist-info/LICENSE.md
torcheck-1.0.1.dist-info/WHEEL
torcheck-1.0.1.dist-info/METADATA
torcheck-1.0.1.dist-info/RECORD
