Metadata-Version: 2.1
Name: torcheck
Version: 1.0.1
Summary: A machine learning sanity check toolkit for PyTorch
Home-page: https://github.com/pengyan510/torcheck
License: MIT
Author: Peng Yan
Author-email: pengyan510@gmail.com
Requires-Python: >=3.8,<4.0
Classifier: License :: OSI Approved :: MIT License
Classifier: Programming Language :: Python :: 3
Classifier: Programming Language :: Python :: 3.8
Classifier: Programming Language :: Python :: 3.9
Requires-Dist: torch (>=1.8,<2.0)
Project-URL: Repository, https://github.com/pengyan510/torcheck
